openlayer_mcp/__init__.py
openlayer_mcp/__main__.py
openlayer_mcp/openlayer_platform.py
openlayer_mcp-0.1.0.dist-info/METADATA
openlayer_mcp-0.1.0.dist-info/WHEEL
openlayer_mcp-0.1.0.dist-info/entry_points.txt
openlayer_mcp-0.1.0.dist-info/RECORD
