Metadata-Version: 2.4
Name: openlayer-mcp
Version: 0.1.0
Summary: MCP server for the Openlayer platform
Requires-Python: >=3.10
Requires-Dist: mcp[cli]>=1.6.0
Requires-Dist: openlayer>=0.2.0a51
